ppf_approx/__init__.py
ppf_approx/lt_fptd.py
ppf_approx/mfpt.py
ppf_approx/ppf.py
ppf_approx-0.1.2.dist-info/LICENSE
ppf_approx-0.1.2.dist-info/METADATA
ppf_approx-0.1.2.dist-info/WHEEL
ppf_approx-0.1.2.dist-info/top_level.txt
ppf_approx-0.1.2.dist-info/RECORD
