Metadata-Version: 2.1
Name: ppf_approx
Version: 0.1.2
Summary: Implementation of the Pade-partial fraction approximation for inverting the Laplace transform of the first passage time distribution.
Author-email: Juan Magalang <jarmsmagalang@gmail.com>
License-File: LICENSE
Requires-Dist: numpy
Requires-Dist: mpmath
Requires-Dist: scipy
